iproxy/__init__.py
iproxy-0.0.0.dist-info/LICENSE
iproxy-0.0.0.dist-info/METADATA
iproxy-0.0.0.dist-info/WHEEL
iproxy-0.0.0.dist-info/top_level.txt
iproxy-0.0.0.dist-info/RECORD
