Metadata-Version: 2.1
Name: iproxy
Version: 0.0.0
Summary: innovata-proxy
Home-page: https://github.com/innovata/iproxy
Author: innovata sambong
Author-email: iinnovata@gmail.com
License: UNKNOWN
Platform: UNKNOWN
Classifier: Programming Language :: Python :: 3
Classifier: License :: OSI Approved :: MIT License
Classifier: Operating System :: OS Independent
